{"utc_time":"2026-4-24 11:31:57.570","name":"","keywords":"WINEVENT_KEYWORD_PROCESS","opcode":"Start ","task":"ProcessStart","level":"Information ","pid":8920,"tid":32508,"process_name":"","image_path":"","metadata":{}}
{"utc_time":"2026-4-24 11:31:57.584","name":"","keywords":"WINEVENT_KEYWORD_PROCESS","opcode":"Start ","task":"ProcessStart","level":"Information ","pid":13956,"tid":27088,"process_name":"","image_path":"","metadata":{}}
{"utc_time":"2026-4-24 11:31:57.721","name":"","keywords":"WINEVENT_KEYWORD_PROCESS","opcode":"Start ","task":"ProcessStart","level":"Information ","pid":13956,"tid":28632,"process_name":"","image_path":"","metadata":{}}
{"utc_time":"2026-4-24 11:31:57.732","name":"","keywords":"WINEVENT_KEYWORD_PROCESS","opcode":"Start ","task":"ProcessStart","level":"Information ","pid":13956,"tid":24780,"process_name":"","image_path":"","metadata":{}}
{"utc_time":"2026-4-24 11:31:57.771","name":"","keywords":"WINEVENT_KEYWORD_PROCESS","opcode":"Start ","task":"ProcessStart","level":"Information ","pid":13956,"tid":1016,"process_name":"","image_path":"","metadata":{}}
{"utc_time":"2026-4-24 11:31:57.911","name":"","keywords":"WINEVENT_KEYWORD_PROCESS","opcode":"Start ","task":"ProcessStart","level":"Information ","pid":13956,"tid":28632,"process_name":"","image_path":"","metadata":{}}
{"utc_time":"2026-4-24 11:31:57.989","name":"","keywords":"WINEVENT_KEYWORD_PROCESS","opcode":"Start ","task":"ProcessStart","level":"Information ","pid":13956,"tid":28632,"process_name":"","image_path":"","metadata":{}}
{"utc_time":"2026-4-24 11:32:7.978","name":"","keywords":"WINEVENT_KEYWORD_PROCESS","opcode":"Start ","task":"ProcessStart","level":"Information ","pid":1216,"tid":22808,"process_name":"","image_path":"","metadata":{}}
{"utc_time":"2026-4-24 11:32:9.682","name":"","keywords":"WINEVENT_KEYWORD_PROCESS","opcode":"Start ","task":"ProcessStart","level":"Information ","pid":1216,"tid":14824,"process_name":"","image_path":"","metadata":{}}
{"utc_time":"2026-4-24 11:32:10.19","name":"","keywords":"WINEVENT_KEYWORD_PROCESS","opcode":"Start ","task":"ProcessStart","level":"Information ","pid":8156,"tid":9520,"process_name":"","image_path":"","metadata":{}}
